Metadata-Version: 2.1
Name: jschon-translation
Version: 0.1.1
Summary: JSON Schema-based JSON document translation
Home-page: https://github.com/marksparkza/jschon-translation
Author: Mark Jacobson
Author-email: mark@saeon.ac.za
License: MIT
Classifier: Intended Audience :: Developers
Classifier: License :: OSI Approved :: MIT License
Classifier: Operating System :: OS Independent
Classifier: Programming Language :: Python :: 3
Classifier: Programming Language :: Python :: 3.8
Classifier: Programming Language :: Python :: 3.9
Classifier: Programming Language :: Python :: 3.10
Classifier: Programming Language :: Python :: 3.11
Classifier: Topic :: Software Development :: Libraries :: Python Modules
Requires-Python: ~=3.8
License-File: LICENSE
Requires-Dist: jschon (>=0.11)
Provides-Extra: dev
Requires-Dist: pytest ; extra == 'dev'
Requires-Dist: coverage ; extra == 'dev'
Provides-Extra: test
Requires-Dist: tox ; extra == 'test'
